bank_statement_reader/AccessBankStatement.py
bank_statement_reader/BankStatementExecutor.py
bank_statement_reader/BankStatementFinalResultResponse.py
bank_statement_reader/BaseBankStatementReport.py
bank_statement_reader/FcmbBankStatement.py
bank_statement_reader/FidelityBankStatement.py
bank_statement_reader/FirstBankStatement.py
bank_statement_reader/GtBankStatement.py
bank_statement_reader/SterlingBankStatement.py
bank_statement_reader/UBABankStatement.py
bank_statement_reader/ZenithBankStatement.py
bank_statement_reader/__init__.py
bank_statement_reader/exceptions/BankStatementProcessingFailed.py
bank_statement_reader/exceptions/InprocessibleBankStatementSupplied.py
bank_statement_reader/exceptions/InvalidBankStatementChoice.py
bank_statement_reader/exceptions/InvalidDataFrameType.py
bank_statement_reader/exceptions/InvalidSalaryRange.py
bank_statement_reader/exceptions/__init__.py
bank_statement_reader_altara-1.4.8.dist-info/METADATA
bank_statement_reader_altara-1.4.8.dist-info/WHEEL
bank_statement_reader_altara-1.4.8.dist-info/RECORD
